pytran/__init__.py
pytran/cache.py
pytran/example.py
pytran/main.py
pytran/utils.py
pytran-0.1.1.dist-info/licenses/LICENSE
pytran-0.1.1.dist-info/WHEEL
pytran-0.1.1.dist-info/METADATA
pytran-0.1.1.dist-info/RECORD
