Metadata-Version: 2.4
Name: pytran
Version: 0.1.1
Summary: Translator, free, and alot of language are supported
Author-email: AYMEN||d9c <aymenmw@proton.me>
License-Expression: GPL-3.0-or-later
License-File: LICENSE
Project-URL: Home, https://github.com/kkkik/pytran
